delta_trace_db/__init__.py
delta_trace_db/db/__init__.py
delta_trace_db/db/delta_trace_db_collection.py
delta_trace_db/db/delta_trace_db_core.py
delta_trace_db/db/util_copy.py
delta_trace_db/dsl/util_dsl_evaluator.py
delta_trace_db/query/__init__.py
delta_trace_db/query/enum_query_type.py
delta_trace_db/query/merge_query_params.py
delta_trace_db/query/query.py
delta_trace_db/query/query_builder.py
delta_trace_db/query/query_execution_result.py
delta_trace_db/query/query_result.py
delta_trace_db/query/raw_query_builder.py
delta_trace_db/query/transaction_query.py
delta_trace_db/query/transaction_query_result.py
delta_trace_db/query/util_field.py
delta_trace_db/query/util_query.py
delta_trace_db/query/cause/__init__.py
delta_trace_db/query/cause/actor.py
delta_trace_db/query/cause/cause.py
delta_trace_db/query/cause/enum_actor_type.py
delta_trace_db/query/cause/permission.py
delta_trace_db/query/cause/temporal_trace/__init__.py
delta_trace_db/query/cause/temporal_trace/temporal_trace.py
delta_trace_db/query/cause/temporal_trace/timestamp_node.py
delta_trace_db/query/nodes/__init__.py
delta_trace_db/query/nodes/comparison_node.py
delta_trace_db/query/nodes/enum_node_type.py
delta_trace_db/query/nodes/enum_value_type.py
delta_trace_db/query/nodes/logical_node.py
delta_trace_db/query/nodes/query_node.py
delta_trace_db/query/sort/__init__.py
delta_trace_db/query/sort/abstract_sort.py
delta_trace_db/query/sort/multi_sort.py
delta_trace_db/query/sort/single_sort.py
delta_trace_db-0.1.2.dist-info/licenses/LICENSE
delta_trace_db-0.1.2.dist-info/METADATA
delta_trace_db-0.1.2.dist-info/WHEEL
delta_trace_db-0.1.2.dist-info/top_level.txt
delta_trace_db-0.1.2.dist-info/RECORD
