Metadata-Version: 2.4
Name: delta_trace_db
Version: 0.1.2
Summary: The NoSQL in-memory database with class-based functionality and detailed operation history tracking.
Author: Masahide Mori
License-Expression: Apache-2.0
Project-URL: Homepage, https://github.com/MasahideMori-SimpleAppli/delta_trace_db_py
Classifier: Programming Language :: Python :: 3
Classifier: Programming Language :: Python :: 3.12
Classifier: Programming Language :: Python :: 3.13
Classifier: Operating System :: OS Independent
Requires-Python: >=3.12
License-File: LICENSE
Requires-Dist: file-state-manager>=3.0.0
Dynamic: license-file
